{
  "items": [
    {
      "entry": "application",
      "subEntry": null,
      "matchType": "exact:entry",
      "hanjaEntry": null,
      "phoneticSigns": [
        {
          "type": "미국∙영국",
          "sign": "ˌæplɪˈkeɪʃn"
        }
      ],
      "pos": [
        {
          "type": "명사",
          "meanings": [
            {
              "meaning": "(특정의 용도·목적에) 적용, 응용, 이용 ((to))",
              "examples": [
                {
                  "text": "practical <b>application</b>",
                  "translatedText": "응용"
                }
              ],
              "originalMeaning": "(특정의 용도·목적에) 적용, 응용, 이용 ((to))"
            },
            {
              "meaning": "특정의 용도[목적]",
              "examples": [],
              "originalMeaning": "특정의 용도[목적]"
            },
            {
              "meaning": "적응성, 응용성, 실용성",
              "examples": [],
              "originalMeaning": "적응성, 응용성, 실용성"
            }
          ]
        }
      ],
      "source": "동아출판 프라임 영한사전",
      "url": "https://en.dict.naver.com/#/entry/enko/ff413564ea78487b894e7b66d58b9101",
      "mUrl": "https://en.dict.naver.com/#/entry/enko/ff413564ea78487b894e7b66d58b9101",
      "expDicTypeForm": "단어",
      "locale": "ko",
      "gdid": "1f92aa85f5e9093d96a958559957595b",
      "expEntrySuperscript": ""
    }
  ],
  "examples": [
    {
      "source": "동아출판 프라임 영한사전",
      "matchType": "allterm:proximity:1.000000",
      "translatedText": "지원 마감 날이 넘어갔다",
      "text": "The deadline for <b>application</b> has expired."
    },
    {
      "source": "동아출판 프라임 영한사전",
      "matchType": "allterm:proximity:1.000000",
      "translatedText": "지원 마감이 어제로 지났다",
      "text": "The time for <b>application</b> expired yesterday."
    },
    {
      "source": "동아출판 프라임 영한사전",
      "matchType": "allterm:proximity:1.000000",
      "translatedText": "항해술은 천문학을 응용한 것이다",
      "text": "Navigation is an <b>application</b> of astronomy."
    },
    {
      "source": "동아출판 프라임 영한사전",
      "matchType": "allterm:proximity:1.000000",
      "translatedText": "그는 지원서를 좀 늦게 내었다",
      "text": "He sent in the <b>application</b> form rather late."
    },
    {
      "source": "동아출판 프라임 영한사전",
      "matchType": "allterm:proximity:1.000000",
      "translatedText": "면허장은 신청하면 얻을 수 있다",
      "text": "A license may be obtained upon <b>application</b>."
    }
  ],
  "isWordType": true
}