{
  "items": [
    {
      "entry": "depend",
      "subEntry": null,
      "matchType": "exact:revert",
      "hanjaEntry": null,
      "phoneticSigns": [
        {
          "type": "미국∙영국",
          "sign": "dipénd"
        }
      ],
      "pos": [
        {
          "type": "자동사",
          "meanings": [
            {
              "meaning": "의존하다, 의지하다 ((on, upon))",
              "examples": [
                {
                  "text": "<b>depend</b> upon another for help",
                  "translatedText": "타인의 원조에 의존하다"
                }
              ],
              "originalMeaning": "의존하다, 의지하다 ((on, upon))"
            },
            {
              "meaning": "믿다, 신뢰하다(rely) ((on, upon))",
              "examples": [
                {
                  "text": "I  <b>depend</b> on your word.",
                  "translatedText": "나는 네 말을 믿는다."
                }
              ],
              "originalMeaning": "믿다, 신뢰하다(rely) ((on, upon))"
            },
            {
              "meaning": "…나름이다 ((on, upon)), …에 달려 있다, 좌우되다",
              "examples": [
                {
                  "text": "<b>depend</b> on the weather",
                  "translatedText": "날씨에 달려 있다"
                }
              ],
              "originalMeaning": "…나름이다 ((on, upon)), …에 달려 있다, 좌우되다"
            }
          ]
        }
      ],
      "source": "동아출판 프라임 영한사전",
      "url": "https://en.dict.naver.com/#/entry/enko/f5c55f2c2c1849a083a517952fab2c4b",
      "mUrl": "https://en.dict.naver.com/#/entry/enko/f5c55f2c2c1849a083a517952fab2c4b",
      "expDicTypeForm": "단어",
      "locale": "ko",
      "gdid": "a39193f1d6f96069da94de550f290052",
      "expEntrySuperscript": ""
    }
  ],
  "examples": [
    {
      "source": "동아출판 프라임 영한사전",
      "matchType": "allterm:proximity:0.000000",
      "translatedText": "나는 네 말을 믿는다.",
      "text": "I <b>depend</b> on your word."
    },
    {
      "source": "동아출판 프라임 영한사전",
      "matchType": "allterm:proximity:0.000000",
      "translatedText": "많은 것이 자네에게 달려 있네.",
      "text": "Much depends upon you."
    },
    {
      "source": "동아출판 프라임 영한사전",
      "matchType": "allterm:proximity:0.000000",
      "translatedText": "모든 것은 하늘에 달렸다",
      "text": "Everything depends on God's will."
    },
    {
      "source": "동아출판 프라임 영한사전",
      "matchType": "allterm:proximity:0.000000",
      "translatedText": "모든 색은 빛에 의해 존재한다.",
      "text": "All colors <b>depend</b> on light."
    },
    {
      "source": "동아출판 프라임 영한사전",
      "matchType": "allterm:proximity:0.000000",
      "translatedText": "승진은 성적의 양부에 따른다",
      "text": "Promotion depends upon one's service."
    }
  ],
  "isWordType": true
}