{
  "items": [
    {
      "entry": "disrupt",
      "subEntry": null,
      "matchType": "exact:subEntry",
      "hanjaEntry": null,
      "phoneticSigns": [
        {
          "type": "미국∙영국",
          "sign": "dɪsˈrʌpt"
        }
      ],
      "pos": [
        {
          "type": "타동사",
          "meanings": [
            {
              "meaning": "<제도·국가 등을> 붕괴시키다, 분열시키다",
              "examples": [],
              "originalMeaning": "<제도·국가 등을> 붕괴시키다, 분열시키다"
            },
            {
              "meaning": "<파티 등을> (일시적으로) 혼란시키다; <교통·통신 등을> 혼란시키다; 일시 불통으로 만들다, 중단[두절]시키다",
              "examples": [],
              "originalMeaning": "<파티 등을> (일시적으로) 혼란시키다; <교통·통신 등을> 혼란시키다; 일시 불통으로 만들다, 중단[두절]시키다"
            }
          ]
        },
        {
          "type": "자동사",
          "meanings": [
            {
              "meaning": "분쇄되다",
              "examples": [],
              "originalMeaning": "분쇄되다"
            }
          ]
        },
        {
          "type": "형용사",
          "meanings": [
            {
              "meaning": "분열한, 분쇄된",
              "examples": [],
              "originalMeaning": "분열한, 분쇄된"
            }
          ]
        }
      ],
      "source": "동아출판 프라임 영한사전",
      "url": "https://en.dict.naver.com/#/entry/enko/39fe1ddd09a142779bd18a936b59b8f6",
      "mUrl": "https://en.dict.naver.com/#/entry/enko/39fe1ddd09a142779bd18a936b59b8f6",
      "expDicTypeForm": "단어",
      "locale": "ko",
      "conjugationList": [
        {
          "type": "3인칭 단수 현재",
          "value": "disrupts"
        },
        {
          "type": "과거형",
          "value": "disrupted"
        },
        {
          "type": "현재 분사",
          "value": "disrupting"
        },
        {
          "type": "과거 분사",
          "value": "disrupted"
        }
      ],
      "aliasConjugation": "disrupts",
      "aliasConjugationPos": "3인칭 단수 현재",
      "gdid": "88be0dddb183ea6f90397029d1017db5",
      "expEntrySuperscript": ""
    }
  ],
  "examples": [
    {
      "source": "동아출판 프라임 영한사전",
      "matchType": "allterm:proximity:0.000000",
      "translatedText": "심한 폭설로 기차 운행이 두절되었다",
      "text": "The train schedule has been disrupted by the heavy snowfall."
    }
  ],
  "isWordType": true
}