{
  "items": [
    {
      "entry": "effectiveness",
      "subEntry": null,
      "matchType": "exact:entry",
      "hanjaEntry": null,
      "phoneticSigns": [
        {
          "type": "미국∙영국",
          "sign": "iféktivnis"
        }
      ],
      "pos": [
        {
          "type": "명사",
          "meanings": [
            {
              "meaning": "유효(성), 효과적임",
              "examples": [],
              "originalMeaning": "유효(성), 효과적임"
            }
          ]
        }
      ],
      "source": "동아출판 프라임 영한사전",
      "url": "https://en.dict.naver.com/#/entry/enko/16dfe9f44a7a434d8e28ecbbbd362072",
      "mUrl": "https://en.dict.naver.com/#/entry/enko/16dfe9f44a7a434d8e28ecbbbd362072",
      "expDicTypeForm": "단어",
      "locale": "ko",
      "gdid": "271937127a859b21e1e3d942acb387d2",
      "expEntrySuperscript": ""
    }
  ],
  "examples": [],
  "isWordType": true
}