{
  "items": [
    {
      "entry": "fan",
      "subEntry": null,
      "matchType": "exact:entry",
      "hanjaEntry": null,
      "phoneticSigns": [
        {
          "type": "미국∙영국",
          "sign": "fǽn"
        }
      ],
      "pos": [
        {
          "type": "명사",
          "meanings": [
            {
              "meaning": "부채; 선풍기; 환풍기, 송풍기",
              "examples": [
                {
                  "text": "an electric <b>fan</b>",
                  "translatedText": "선풍기"
                }
              ],
              "originalMeaning": "부채; 선풍기; 환풍기, 송풍기"
            },
            {
              "meaning": "부채꼴의 물건 ((추진기의 날개·풍차의 날개·새의 꽁지 등))",
              "examples": [],
              "originalMeaning": "부채꼴의 물건 ((추진기의 날개·풍차의 날개·새의 꽁지 등))"
            }
          ]
        },
        {
          "type": "타동사",
          "meanings": [
            {
              "meaning": "<얼굴 등을> (부채 등으로) 부치다, <바람을> (부채 등으로) 보내다, <바람이> …에 솔솔 불다, <얼굴을> 만지다",
              "examples": [
                {
                  "text": "<b>fan</b> one's face with a notebook",
                  "translatedText": "노트로 얼굴을 부치다"
                }
              ],
              "originalMeaning": "<얼굴 등을> (부채 등으로) 부치다, <바람을> (부채 등으로) 보내다, <바람이> …에 솔솔 불다, <얼굴을> 만지다"
            },
            {
              "meaning": "<감정을> 부채질하다, 선동하다, 부추기다",
              "examples": [
                {
                  "text": "<b>fan</b> emotions",
                  "translatedText": "감정을 부추기다"
                }
              ],
              "originalMeaning": "<감정을> 부채질하다, 선동하다, 부추기다"
            }
          ]
        },
        {
          "type": "자동사",
          "meanings": [
            {
              "meaning": "(부채꼴로) 펼쳐지다 ((out))",
              "examples": [
                {
                  "text": "The forest fire fanned out in all directions.",
                  "translatedText": "산불이 사방팔방으로 번졌다."
                }
              ],
              "originalMeaning": "(부채꼴로) 펼쳐지다 ((out))"
            },
            {
              "meaning": "삼진당하다",
              "examples": [],
              "originalMeaning": "삼진당하다"
            }
          ]
        }
      ],
      "source": "동아출판 프라임 영한사전",
      "url": "https://en.dict.naver.com/#/entry/enko/2c8b2cb61d9947509d37472ddd722d70",
      "mUrl": "https://en.dict.naver.com/#/entry/enko/2c8b2cb61d9947509d37472ddd722d70",
      "expDicTypeForm": "단어",
      "locale": "ko",
      "conjugationList": [
        {
          "type": "3인칭 단수 현재",
          "value": "fans"
        },
        {
          "type": "과거형",
          "value": "fanned"
        },
        {
          "type": "현재 분사",
          "value": "fanning"
        },
        {
          "type": "과거 분사",
          "value": "fanned"
        }
      ],
      "aliasConjugation": "fans",
      "aliasConjugationPos": "3인칭 단수 현재",
      "gdid": "7d303a29fc0d379afd0e1a05399ba219",
      "expEntrySuperscript": "1"
    },
    {
      "entry": "fan",
      "subEntry": null,
      "matchType": "exact:entry",
      "hanjaEntry": null,
      "phoneticSigns": [
        {
          "type": "미국∙영국",
          "sign": "fǽn"
        }
      ],
      "pos": [
        {
          "type": "명사",
          "meanings": [
            {
              "meaning": "(영화·스포츠 등의) 팬, …광(狂)",
              "examples": [
                {
                  "text": "a baseball[film] <b>fan</b>",
                  "translatedText": "야구[영화] 팬"
                }
              ],
              "originalMeaning": "(영화·스포츠 등의) 팬, …광(狂)"
            }
          ]
        }
      ],
      "source": "동아출판 프라임 영한사전",
      "url": "https://en.dict.naver.com/#/entry/enko/bac64ab0f3ff435b86545e512d50924e",
      "mUrl": "https://en.dict.naver.com/#/entry/enko/bac64ab0f3ff435b86545e512d50924e",
      "expDicTypeForm": "단어",
      "locale": "ko",
      "aliasConjugation": "fans",
      "aliasConjugationPos": "3인칭 단수 현재",
      "gdid": "3a83ea5675d6b0a8e548404e6538e185",
      "expEntrySuperscript": "2"
    }
  ],
  "examples": [
    {
      "source": "동아출판 프라임 영한사전",
      "matchType": "allterm:proximity:1.000000",
      "translatedText": "산들바람이 우리의 얼굴을 어루만졌다",
      "text": "The breeze fanned our cheeks."
    },
    {
      "source": "동아출판 프라임 영한사전",
      "matchType": "allterm:proximity:1.000000",
      "translatedText": "시원한 산들바람이 바닷가를 불어 갔다.",
      "text": "A cool breeze fanned the shore."
    },
    {
      "source": "동아출판 프라임 영한사전",
      "matchType": "allterm:proximity:1.000000",
      "translatedText": "그는 카드를 테이블 위에 부채꼴로 펼쳤다.",
      "text": "He fanned out the cards on the table."
    },
    {
      "source": "동아출판 프라임 영한사전",
      "matchType": "allterm:proximity:1.000000",
      "translatedText": "그의 말은 인종적 긴장 상태에 불을 부쳤다",
      "text": "His remarks fanned the flames of racial tension."
    },
    {
      "source": "동아출판 프라임 영한사전",
      "matchType": "allterm:proximity:1.000000",
      "translatedText": "그녀는 부채로 잠자는 아이에게서 모기를 쫓았다.",
      "text": "She fanned away a mosquito from the sleeping child."
    }
  ],
  "isWordType": true
}