{
  "items": [
    {
      "entry": "layer",
      "subEntry": null,
      "matchType": "exact:entry",
      "hanjaEntry": null,
      "phoneticSigns": [
        {
          "type": "미국식",
          "sign": "ˈler"
        }
      ],
      "pos": [
        {
          "type": "명사",
          "meanings": [
            {
              "meaning": "층(層), 쌓은[겹친, 칠한] 켜",
              "examples": [],
              "originalMeaning": "층(層), 쌓은[겹친, 칠한] 켜"
            },
            {
              "meaning": "놓는[쌓는, 까는] 사람; 계획자",
              "examples": [],
              "originalMeaning": "놓는[쌓는, 까는] 사람; 계획자"
            }
          ]
        },
        {
          "type": "타동사",
          "meanings": [
            {
              "meaning": "층으로 만들다, 층상으로 쌓아 올리다",
              "examples": [],
              "originalMeaning": "층으로 만들다, 층상으로 쌓아 올리다"
            },
            {
              "meaning": "<옷을> 껴입다",
              "examples": [],
              "originalMeaning": "<옷을> 껴입다"
            }
          ]
        },
        {
          "type": "자동사",
          "meanings": [
            {
              "meaning": "(땅과 접한) 가지 부분에서 뿌리를 내리다, 층을 이루다; <작물이> (비바람에) 쓰러지다",
              "examples": [],
              "originalMeaning": "(땅과 접한) 가지 부분에서 뿌리를 내리다, 층을 이루다; <작물이> (비바람에) 쓰러지다"
            }
          ]
        }
      ],
      "source": "동아출판 프라임 영한사전",
      "url": "https://en.dict.naver.com/#/entry/enko/ef6c5fa9a9034e2699882b1206e39785",
      "mUrl": "https://en.dict.naver.com/#/entry/enko/ef6c5fa9a9034e2699882b1206e39785",
      "expDicTypeForm": "단어",
      "locale": "ko",
      "conjugationList": [
        {
          "type": "3인칭 단수 현재",
          "value": "layers"
        },
        {
          "type": "과거형",
          "value": "layered"
        },
        {
          "type": "현재 분사",
          "value": "layering"
        },
        {
          "type": "과거 분사",
          "value": "layered"
        }
      ],
      "aliasConjugation": "layers",
      "aliasConjugationPos": "3인칭 단수 현재",
      "gdid": "4a6c44feed0a6f8f49e79885d430f8e7",
      "expEntrySuperscript": ""
    }
  ],
  "examples": [
    {
      "source": "동아출판 프라임 영한사전",
      "matchType": "allterm:proximity:1.000000",
      "translatedText": "이 닭은 달걀을 잘 낳는다",
      "text": "This hen is a good <b>layer</b>."
    },
    {
      "source": "동아출판 프라임 영한사전",
      "matchType": "allterm:proximity:1.000000",
      "translatedText": "씨 위에 살짝 흙을 덮어 주어라",
      "text": "Cover the seeds with a thin <b>layer</b> of soil[earth]."
    },
    {
      "source": "동아출판 프라임 영한사전",
      "matchType": "allterm:proximity:1.000000",
      "translatedText": "책상 위에 먼지가 잔뜩 앉아 있다",
      "text": "There is a thick <b>layer</b> of dust on the desk."
    },
    {
      "source": "동아출판 프라임 영한사전",
      "matchType": "allterm:proximity:1.000000",
      "translatedText": "강에 살얼음이 잡혔다",
      "text": "A thin <b>layer</b> of ice covered the river."
    },
    {
      "source": "동아출판 프라임 영한사전",
      "matchType": "allterm:proximity:1.000000",
      "translatedText": "장판이 들떴다",
      "text": "A <b>layer</b> of oil paper has come off the floor."
    }
  ],
  "isWordType": true
}