{
  "items": [
    {
      "entry": "rework",
      "subEntry": null,
      "matchType": "exact:entry",
      "hanjaEntry": null,
      "phoneticSigns": [
        {
          "type": "미국식",
          "sign": "│riː│wɜːrk"
        }
      ],
      "pos": [
        {
          "type": "타동사",
          "meanings": [
            {
              "meaning": "개정하다, 뜯어고치다; 재생하다, 재가공하다",
              "examples": [],
              "originalMeaning": "개정하다, 뜯어고치다; 재생하다, 재가공하다"
            },
            {
              "meaning": "<식물을> 접목으로 변종을 만들다",
              "examples": [],
              "originalMeaning": "<식물을> 접목으로 변종을 만들다"
            }
          ]
        },
        {
          "type": "명사",
          "meanings": [
            {
              "meaning": "다시 만듦, 재가공",
              "examples": [],
              "originalMeaning": "다시 만듦, 재가공"
            }
          ]
        }
      ],
      "source": "동아출판 프라임 영한사전",
      "url": "https://en.dict.naver.com/#/entry/enko/bf875cedb52d4d8e9afcb73c7da01742",
      "mUrl": "https://en.dict.naver.com/#/entry/enko/bf875cedb52d4d8e9afcb73c7da01742",
      "expDicTypeForm": "단어",
      "locale": "ko",
      "conjugationList": [
        {
          "type": "3인칭 단수 현재",
          "value": "reworks"
        },
        {
          "type": "과거형",
          "value": "reworked"
        },
        {
          "type": "현재 분사",
          "value": "reworking"
        },
        {
          "type": "과거 분사",
          "value": "reworked"
        }
      ],
      "aliasConjugation": "reworks",
      "aliasConjugationPos": "3인칭 단수 현재",
      "gdid": "72e321ce7b354f2835b567519d480045",
      "expEntrySuperscript": ""
    }
  ],
  "examples": [],
  "isWordType": true
}