{
  "items": [
    {
      "entry": "underestimate",
      "subEntry": null,
      "matchType": "exact:entry",
      "hanjaEntry": null,
      "phoneticSigns": null,
      "pos": [
        {
          "type": "타동사",
          "meanings": [
            {
              "meaning": "낮게[적게] 어림하다; 과소평가하다, 얕잡아 보다, 경시하다",
              "examples": [
                {
                  "text": "<b>underestimate</b> the problem[the enemy's strength]",
                  "translatedText": "문제[적의 힘]를 과소평가하다"
                }
              ],
              "originalMeaning": "낮게[적게] 어림하다; 과소평가하다, 얕잡아 보다, 경시하다"
            }
          ]
        },
        {
          "type": "자동사",
          "meanings": [
            {
              "meaning": "너무 싸게 어림[견적]하다",
              "examples": [],
              "originalMeaning": "너무 싸게 어림[견적]하다"
            }
          ]
        },
        {
          "type": "명사",
          "meanings": [
            {
              "meaning": "싼 어림[견적]; 과소평가, 경시",
              "examples": [],
              "originalMeaning": "싼 어림[견적]; 과소평가, 경시"
            }
          ]
        }
      ],
      "source": "동아출판 프라임 영한사전",
      "url": "https://en.dict.naver.com/#/entry/enko/7c5dd0d375ab491eab5e565724516671",
      "mUrl": "https://en.dict.naver.com/#/entry/enko/7c5dd0d375ab491eab5e565724516671",
      "expDicTypeForm": "단어",
      "locale": "ko",
      "conjugationList": [
        {
          "type": "3인칭 단수 현재",
          "value": "underestimates"
        },
        {
          "type": "과거형",
          "value": "underestimated"
        },
        {
          "type": "현재 분사",
          "value": "underestimating"
        },
        {
          "type": "과거 분사",
          "value": "underestimated"
        }
      ],
      "aliasConjugation": "underestimates",
      "aliasConjugationPos": "3인칭 단수 현재",
      "gdid": "6b2a27f5e9af5ec831a6c9aaecdfc747",
      "expEntrySuperscript": ""
    }
  ],
  "examples": [
    {
      "source": "동아출판 프라임 영한사전",
      "matchType": "allterm:proximity:1.000000",
      "translatedText": "내가 너에게 그를 과소평가하지 말라고 말했지",
      "text": "I told you not to <b>underestimate</b> him."
    },
    {
      "source": "동아출판 프라임 영한사전",
      "matchType": "allterm:proximity:1.000000",
      "translatedText": "우리는 흔히 아이들의 회복력을 과소평가한다",
      "text": "Frequently we <b>underestimate</b> children's resilience."
    },
    {
      "source": "동아출판 프라임 영한사전",
      "matchType": "allterm:proximity:1.000000",
      "translatedText": "여전히 그를 과소평가하는 사람이 많다고 생각한다",
      "text": "I think a lot of people still <b>underestimate</b> him."
    },
    {
      "source": "동아출판 프라임 영한사전",
      "matchType": "allterm:proximity:1.000000",
      "translatedText": "어린애라고 우습게보지 마라",
      "text": "Don't <b>underestimate</b> him, just because he is a boy."
    }
  ],
  "isWordType": true
}